CHANGELOG.txt
MANIFEST.in
README.md
README.txt
requirements.txt
setup.py
json2tree/__init__.py
json2tree/__main__.py
json2tree.egg-info/PKG-INFO
json2tree.egg-info/SOURCES.txt
json2tree.egg-info/dependency_links.txt
json2tree.egg-info/entry_points.txt
json2tree.egg-info/top_level.txt
json2tree/theme_1/__init__.py
json2tree/theme_1/css.py
json2tree/theme_1/html.py
json2tree/theme_1/js.py
json2tree/theme_2/__init__.py
json2tree/theme_2/css.py
json2tree/theme_2/html.py
json2tree/theme_2/js.py